amin_qvm/__init__.py
amin_qvm-2.0.0.dist-info/METADATA
amin_qvm-2.0.0.dist-info/WHEEL
amin_qvm-2.0.0.dist-info/top_level.txt
amin_qvm-2.0.0.dist-info/RECORD
