Metadata-Version: 2.1
Name: amin-qvm
Version: 2.0.0
Summary: Amin-QVM: Quantum Computing Library With Built In Novum QVM
Home-page: https://pypi.org/project/amin-qvm/
Author: Amin Alogaili
Author-email: aminalogai@aol.com
Keywords: quantum computing library simulation amin alogaili QVM aminalogaili novum
Classifier: Development Status :: 5 - Production/Stable
Classifier: Intended Audience :: Developers
Classifier: License :: OSI Approved :: MIT License
Classifier: Operating System :: OS Independent
Classifier: Programming Language :: Python :: 3
Classifier: Programming Language :: Python :: 3.6
Classifier: Programming Language :: Python :: 3.7
Classifier: Programming Language :: Python :: 3.8
Requires-Python: >=3.8
Requires-Dist: numpy
Requires-Dist: pandas
